[
    {
        "type": "current_source",
        "id": "Iq",
        "N1": "0",
        "N2": "1",
        "I": 4
    },
    {
        "type": "resistor",
        "id": "R1",
        "N1": "1",
        "N2": "0",
        "R": 15 
    },
    {
        "type": "resistor",
        "id": "R2",
        "N1": "1",
        "N2": "2",
        "R": 5
    },
    {
        "type": "resistor",
        "id": "R3",
        "N1": "2",
        "N2": "0",
        "R": 20
    },
    {
        "type": "voltage_source",
        "id": "Uq",
        "N1": "3",
        "N2": "2",
        "U": 120
    },
    {
        "type": "resistor",
        "id": "R4",
        "N1": "3",
        "N2": "0",
        "R": 20
    }
]