{"circuit": {"components": [{"type": "complex_voltage_source", "id": "U1", "nodes": ["2", "0"], "value": {"V_real": 1.0, "V_imag": -2.0, "R": 0, "X": 0}}, {"type": "impedance", "id": "Z1", "nodes": ["2", "0"], "value": {"R": 10.0, "X": 10.0}}, {"type": "ground", "id": "0", "nodes": ["0"], "value": {}}, {"type": "impedance", "id": "Z2", "nodes": ["2", "3"], "value": {"R": 20.0, "X": 0.0}}, {"type": "impedance", "id": "Z3", "nodes": ["3", "0"], "value": {"R": 30.0, "X": 0.0}}]}, "simple_circuit": [{"type": "complex_voltage_source", "name": "U1", "reverse": true, "values": {"_userparams": {"V": null, "name": "U1", "reverse": false, "precision": 2, "d": "up", "drop": {"type": "Point", "values": [4.0, 0]}}, "segments": [{"type": "Segment", "values": {"path": [{"type": "Point", "values": [-3.0, 0]}, {"type": "Point", "values": [0, 0]}, {"type": "Point", "values": [0, 0]}, {"type": "Point", "values": [NaN, NaN]}, {"type": "Point", "values": [1, 0]}, {"type": "Point", "values": [1, 0]}, {"type": "Point", "values": [4.0, 0]}], "zorder": null, "color": null, "fill": null, "lw": null, "ls": null, "arrow": null, "arrowwidth": 0.15, "arrowlength": 0.25, "clip": null, "capstyle": null, "joinstyle": null, "visible": true}}, {"type": "SegmentCircle", "values": {"center": [0.5, 0], "radius": 0.5, "color": null, "lw": null, "ls": null, "fill": null, "clip": null, "zorder": null, "ref": null, "visible": true}}, {"type": "Segment", "values": {"path": [{"type": "Point", "values": [0.25, -0.1]}, {"type": "Point", "values": [0.25, 0.1]}], "zorder": null, "color": null, "fill": null, "lw": null, "ls": null, "arrow": null, "arrowwidth": 0.15, "arrowlength": 0.25, "clip": null, "capstyle": null, "joinstyle": null, "visible": true}}, {"type": "Segment", "values": {"path": [{"type": "Point", "values": [0.65, 0]}, {"type": "Point", "values": [0.85, 0]}], "zorder": null, "color": null, "fill": null, "lw": null, "ls": null, "arrow": null, "arrowwidth": 0.15, "arrowlength": 0.25, "clip": null, "capstyle": null, "joinstyle": null, "visible": true}}, {"type": "Segment", "values": {"path": [{"type": "Point", "values": [0.75, -0.1]}, {"type": "Point", "values": [0.75, 0.1]}], "zorder": null, "color": null, "fill": null, "lw": null, "ls": null, "arrow": null, "arrowwidth": 0.15, "arrowlength": 0.25, "clip": null, "capstyle": null, "joinstyle": null, "visible": true}}, {"type": "Segment", "values": {"path": [{"type": "Point", "values": [1.5, 0.7]}, {"type": "Point", "values": [-0.5, 0.7]}], "zorder": null, "color": "#02468F", "fill": null, "lw": null, "ls": null, "arrow": "->", "arrowwidth": 0.3, "arrowlength": 0.4, "clip": null, "capstyle": null, "joinstyle": null, "visible": true}}, {"type": "SegmentText", "values": {"pos": {"type": "Point", "values": [0.5, 1.2000000000000002]}, "label": "U1=1.0V-j2.0V", "align": ["center", "center"], "font": "sans-serif", "mathfont": null, "fontsize": 14.0, "color": "#02468F", "rotation": 90, "rotation_mode": null, "rotation_global": true, "clip": null, "zorder": null, "visible": true}}], "params": {"unit": 7, "inches_per_unit": 0.5, "lblofst": 0.1, "fontsize": 14.0, "font": "sans-serif", "color": "black", "lw": 2.0, "ls": "-", "fill": null, "margin": 0.1, "leadcolor": null, "dotradius": 0.075, "theta": 90, "V": null, "name": "U1", "reverse": false, "precision": 2, "d": "up", "drop": {"type": "Point", "values": [4.0, 0]}}, "anchors": {"value_label": [0.5, 1.1], "v_label": [0.5, -1.1], "i_label": [1.2, 0.3], "s_label": [0.5, 1.5], "istart": {"type": "Point", "values": [0, 0]}, "iend": {"type": "Point", "values": [1, 0]}, "start": {"type": "Point", "values": [-3.0, 0]}, "end": {"type": "Point", "values": [4.0, 0]}, "center": {"type": "Point", "values": [0.5, 0.0]}}, "absanchors": {"start": {"type": "Point", "values": [0.0, 0.0]}, "end": {"type": "Point", "values": [4.286263797015736e-16, 7.0]}, "center": {"type": "Point", "values": [2.143131898507868e-16, 3.5]}, "value_label": {"type": "Point", "values": [-1.0999999999999999, 3.5]}, "v_label": {"type": "Point", "values": [1.1000000000000003, 3.5]}, "i_label": {"type": "Point", "values": [-0.2999999999999997, 4.2]}, "s_label": {"type": "Point", "values": [-1.4999999999999998, 3.5]}, "istart": {"type": "Point", "values": [1.8369701987210297e-16, 3.0]}, "iend": {"type": "Point", "values": [2.4492935982947064e-16, 4.0]}, "xy": {"type": "Point", "values": [1.8369701987210297e-16, 3.0]}}, "transform": {"type": "Transform", "values": {"theta": 90, "globalshift": {"type": "Point", "values": [0, 0]}, "localshift": {"type": "Point", "values": [3.0, 0]}, "zoom": {"type": "Point", "values": [1, 1]}}}, "absdrop": [{"type": "Point", "values": [4.286263797015736e-16, 7.0]}, 90]}}, {"type": "line", "name": "", "reverse": false, "values": {"_userparams": {"d": "right", "drop": {"type": "Point", "values": [3.5, 0]}}, "segments": [{"type": "Segment", "values": {"path": [{"type": "Point", "values": [-3.5, 0]}, {"type": "Point", "values": [0, 0]}, {"type": "Point", "values": [3.5, 0]}], "zorder": null, "color": null, "fill": null, "lw": null, "ls": null, "arrow": null, "arrowwidth": 0.15, "arrowlength": 0.25, "clip": null, "capstyle": null, "joinstyle": null, "visible": true}}], "params": {"unit": 7, "inches_per_unit": 0.5, "lblofst": 0.1, "fontsize": 14.0, "font": "sans-serif", "color": "black", "lw": 2.0, "ls": "-", "fill": null, "margin": 0.1, "leadcolor": null, "dotradius": 0.075, "arrowwidth": 0.15, "arrowlength": 0.25, "d": "right", "drop": {"type": "Point", "values": [3.5, 0]}}, "anchors": {"istart": {"type": "Point", "values": [0, 0]}, "iend": {"type": "Point", "values": [0, 0]}, "start": {"type": "Point", "values": [-3.5, 0]}, "end": {"type": "Point", "values": [3.5, 0]}, "center": {"type": "Point", "values": [0.0, 0.0]}}, "absanchors": {"start": {"type": "Point", "values": [4.286263797015736e-16, 7.0]}, "end": {"type": "Point", "values": [7.0, 7.0]}, "center": {"type": "Point", "values": [3.5000000000000004, 7.0]}, "istart": {"type": "Point", "values": [3.5000000000000004, 7.0]}, "iend": {"type": "Point", "values": [3.5000000000000004, 7.0]}, "xy": {"type": "Point", "values": [3.5000000000000004, 7.0]}}, "transform": {"type": "Transform", "values": {"theta": 0, "globalshift": {"type": "Point", "values": [4.286263797015736e-16, 7.0]}, "localshift": {"type": "Point", "values": [3.5, 0]}, "zoom": {"type": "Point", "values": [1, 1]}}}, "absdrop": [{"type": "Point", "values": [7.0, 7.0]}, 0]}}, {"type": "impedance", "name": "Z1", "reverse": false, "values": {"_userparams": {"Z": null, "name": "Z1", "precision": 2, "reverse": false, "d": "down", "drop": {"type": "Point", "values": [4.0, 0]}}, "segments": [{"type": "Segment", "values": {"path": [{"type": "Point", "values": [-3.0, 0]}, {"type": "Point", "values": [0, 0]}, {"type": "Point", "values": [0.08333333333333333, 0.25]}, {"type": "Point", "values": [0.25, -0.25]}, {"type": "Point", "values": [0.41666666666666663, 0.25]}, {"type": "Point", "values": [0.5833333333333333, -0.25]}, {"type": "Point", "values": [0.75, 0.25]}, {"type": "Point", "values": [0.9166666666666666, -0.25]}, {"type": "Point", "values": [1.0, 0]}, {"type": "Point", "values": [4.0, 0]}], "zorder": null, "color": null, "fill": null, "lw": null, "ls": null, "arrow": null, "arrowwidth": 0.15, "arrowlength": 0.25, "clip": null, "capstyle": null, "joinstyle": null, "visible": true}}, {"type": "SegmentText", "values": {"pos": {"type": "Point", "values": [0.5, -0.5]}, "label": "Z1=10\u03a9 + j10\u03a9", "align": ["center", "center"], "font": "sans-serif", "mathfont": null, "fontsize": 14.0, "color": "black", "rotation": 90, "rotation_mode": null, "rotation_global": true, "clip": null, "zorder": null, "visible": true}}], "params": {"unit": 7, "inches_per_unit": 0.5, "lblofst": 0.1, "fontsize": 14.0, "font": "sans-serif", "color": "black", "lw": 2.0, "ls": "-", "fill": null, "margin": 0.1, "leadcolor": null, "dotradius": 0.075, "Z": null, "name": "Z1", "precision": 2, "reverse": false, "d": "down", "drop": {"type": "Point", "values": [4.0, 0]}}, "anchors": {"value_label": [0.5, -0.6], "v_label": [0.5, 0.3], "s_label": [0.5, -1.2], "istart": {"type": "Point", "values": [0, 0]}, "iend": {"type": "Point", "values": [1.0, 0]}, "start": {"type": "Point", "values": [-3.0, 0]}, "end": {"type": "Point", "values": [4.0, 0]}, "center": {"type": "Point", "values": [0.5, 0.0]}}, "absanchors": {"start": {"type": "Point", "values": [7.0, 7.0]}, "end": {"type": "Point", "values": [6.999999999999999, 0.0]}, "center": {"type": "Point", "values": [6.999999999999999, 3.5]}, "value_label": {"type": "Point", "values": [6.3999999999999995, 3.5]}, "v_label": {"type": "Point", "values": [7.299999999999999, 3.5]}, "s_label": {"type": "Point", "values": [5.799999999999999, 3.5]}, "istart": {"type": "Point", "values": [6.999999999999999, 4.0]}, "iend": {"type": "Point", "values": [6.999999999999999, 3.0]}, "xy": {"type": "Point", "values": [6.999999999999999, 4.0]}}, "transform": {"type": "Transform", "values": {"theta": 270, "globalshift": {"type": "Point", "values": [7.0, 7.0]}, "localshift": {"type": "Point", "values": [3.0, 0]}, "zoom": {"type": "Point", "values": [1, 1]}}}, "absdrop": [{"type": "Point", "values": [6.999999999999999, 0.0]}, 270]}}, {"type": "line", "name": "", "reverse": false, "values": {"_userparams": {"d": "left", "drop": {"type": "Point", "values": [3.5, 0]}}, "segments": [{"type": "Segment", "values": {"path": [{"type": "Point", "values": [-3.5, 0]}, {"type": "Point", "values": [0, 0]}, {"type": "Point", "values": [3.5, 0]}], "zorder": null, "color": null, "fill": null, "lw": null, "ls": null, "arrow": null, "arrowwidth": 0.15, "arrowlength": 0.25, "clip": null, "capstyle": null, "joinstyle": null, "visible": true}}], "params": {"unit": 7, "inches_per_unit": 0.5, "lblofst": 0.1, "fontsize": 14.0, "font": "sans-serif", "color": "black", "lw": 2.0, "ls": "-", "fill": null, "margin": 0.1, "leadcolor": null, "dotradius": 0.075, "arrowwidth": 0.15, "arrowlength": 0.25, "d": "left", "drop": {"type": "Point", "values": [3.5, 0]}}, "anchors": {"istart": {"type": "Point", "values": [0, 0]}, "iend": {"type": "Point", "values": [0, 0]}, "start": {"type": "Point", "values": [-3.5, 0]}, "end": {"type": "Point", "values": [3.5, 0]}, "center": {"type": "Point", "values": [0.0, 0.0]}}, "absanchors": {"start": {"type": "Point", "values": [6.999999999999999, 0.0]}, "end": {"type": "Point", "values": [-8.881784197001252e-16, 8.572527594031472e-16]}, "center": {"type": "Point", "values": [3.499999999999999, 4.286263797015736e-16]}, "istart": {"type": "Point", "values": [3.499999999999999, 4.286263797015736e-16]}, "iend": {"type": "Point", "values": [3.499999999999999, 4.286263797015736e-16]}, "xy": {"type": "Point", "values": [3.499999999999999, 4.286263797015736e-16]}}, "transform": {"type": "Transform", "values": {"theta": 180, "globalshift": {"type": "Point", "values": [6.999999999999999, 0.0]}, "localshift": {"type": "Point", "values": [3.5, 0]}, "zoom": {"type": "Point", "values": [1, 1]}}}, "absdrop": [{"type": "Point", "values": [-8.881784197001252e-16, 8.572527594031472e-16]}, 180]}}, {"type": "ground", "name": "0", "reverse": false, "values": {"_userparams": {"name": "0", "theta": 0, "drop": [0, 0]}, "segments": [{"type": "Segment", "values": {"path": [{"type": "Point", "values": [0, 0]}, {"type": "Point", "values": [0, -0.4]}, {"type": "Point", "values": [-0.25, -0.4]}, {"type": "Point", "values": [0.25, -0.4]}, {"type": "Point", "values": [NaN, NaN]}, {"type": "Point", "values": [-0.175, -0.52]}, {"type": "Point", "values": [0.175, -0.52]}, {"type": "Point", "values": [NaN, NaN]}, {"type": "Point", "values": [-0.05, -0.64]}, {"type": "Point", "values": [0.05, -0.64]}], "zorder": null, "color": null, "fill": null, "lw": null, "ls": null, "arrow": null, "arrowwidth": 0.15, "arrowlength": 0.25, "clip": null, "capstyle": null, "joinstyle": null, "visible": true}}], "params": {"unit": 7, "inches_per_unit": 0.5, "lblofst": 0.1, "fontsize": 14.0, "font": "sans-serif", "color": "black", "lw": 2.0, "ls": "-", "fill": null, "margin": 0.1, "name": "0", "theta": 0, "drop": [0, 0]}, "anchors": {"start": [0, 0], "center": [0, 0], "end": [0, 0], "NE": [0.5, 0.1], "NW": [-0.5, 0.1], "SE": [0.5, -0.3], "SW": [-0.5, -0.3]}, "absanchors": {"start": {"type": "Point", "values": [-8.881784197001252e-16, 8.572527594031472e-16]}, "center": {"type": "Point", "values": [-8.881784197001252e-16, 8.572527594031472e-16]}, "end": {"type": "Point", "values": [-8.881784197001252e-16, 8.572527594031472e-16]}, "NE": {"type": "Point", "values": [0.4999999999999991, 0.10000000000000087]}, "NW": {"type": "Point", "values": [-0.5000000000000009, 0.10000000000000087]}, "SE": {"type": "Point", "values": [0.4999999999999991, -0.29999999999999916]}, "SW": {"type": "Point", "values": [-0.5000000000000009, -0.29999999999999916]}, "xy": {"type": "Point", "values": [-8.881784197001252e-16, 8.572527594031472e-16]}}, "transform": {"type": "Transform", "values": {"theta": 0, "globalshift": {"type": "Point", "values": [-8.881784197001252e-16, 8.572527594031472e-16]}, "localshift": {"type": "Point", "values": [0, 0]}, "zoom": {"type": "Point", "values": [1, 1]}}}, "absdrop": [{"type": "Point", "values": [-8.881784197001252e-16, 8.572527594031472e-16]}, 180]}}, {"type": "impedance", "name": "Z2", "reverse": false, "values": {"_userparams": {"Z": 20, "name": "Z2", "reverse": false, "at": {"type": "Point", "values": [7.0, 7.0]}, "d": "right", "drop": {"type": "Point", "values": [4.0, 0]}}, "segments": [{"type": "Segment", "values": {"path": [{"type": "Point", "values": [-3.0, 0]}, {"type": "Point", "values": [0, 0]}, {"type": "Point", "values": [0.08333333333333333, 0.25]}, {"type": "Point", "values": [0.25, -0.25]}, {"type": "Point", "values": [0.41666666666666663, 0.25]}, {"type": "Point", "values": [0.5833333333333333, -0.25]}, {"type": "Point", "values": [0.75, 0.25]}, {"type": "Point", "values": [0.9166666666666666, -0.25]}, {"type": "Point", "values": [1.0, 0]}, {"type": "Point", "values": [4.0, 0]}], "zorder": null, "color": null, "fill": null, "lw": null, "ls": null, "arrow": null, "arrowwidth": 0.15, "arrowlength": 0.25, "clip": null, "capstyle": null, "joinstyle": null, "visible": true}}, {"type": "SegmentText", "values": {"pos": {"type": "Point", "values": [0.5, 0.4]}, "label": "Z2=20.0\u03a9", "align": ["center", "bottom"], "font": "sans-serif", "mathfont": null, "fontsize": 14.0, "color": "black", "rotation": 0, "rotation_mode": null, "rotation_global": true, "clip": null, "zorder": null, "visible": true}}], "params": {"unit": 7, "inches_per_unit": 0.5, "lblofst": 0.1, "fontsize": 14.0, "font": "sans-serif", "color": "black", "lw": 2.0, "ls": "-", "fill": null, "margin": 0.1, "leadcolor": null, "dotradius": 0.075, "Z": 20, "name": "Z2", "reverse": false, "at": {"type": "Point", "values": [7.0, 7.0]}, "d": "right", "drop": {"type": "Point", "values": [4.0, 0]}}, "anchors": {"value_label": [0.5, 0.3], "v_label": [0.5, -1.1], "s_label": [0.5, 0.9], "istart": {"type": "Point", "values": [0, 0]}, "iend": {"type": "Point", "values": [1.0, 0]}, "start": {"type": "Point", "values": [-3.0, 0]}, "end": {"type": "Point", "values": [4.0, 0]}, "center": {"type": "Point", "values": [0.5, 0.0]}}, "absanchors": {"start": {"type": "Point", "values": [7.0, 7.0]}, "end": {"type": "Point", "values": [14.0, 7.0]}, "center": {"type": "Point", "values": [10.5, 7.0]}, "value_label": {"type": "Point", "values": [10.5, 7.3]}, "v_label": {"type": "Point", "values": [10.5, 5.9]}, "s_label": {"type": "Point", "values": [10.5, 7.9]}, "istart": {"type": "Point", "values": [10.0, 7.0]}, "iend": {"type": "Point", "values": [11.0, 7.0]}, "xy": {"type": "Point", "values": [10.0, 7.0]}}, "transform": {"type": "Transform", "values": {"theta": 0, "globalshift": {"type": "Point", "values": [7.0, 7.0]}, "localshift": {"type": "Point", "values": [3.0, 0]}, "zoom": {"type": "Point", "values": [1, 1]}}}, "absdrop": [{"type": "Point", "values": [14.0, 7.0]}, 0]}}, {"type": "impedance", "name": "Z3", "reverse": false, "values": {"_userparams": {"Z": 30, "name": "Z3", "reverse": false, "d": "down", "drop": {"type": "Point", "values": [4.0, 0]}}, "segments": [{"type": "Segment", "values": {"path": [{"type": "Point", "values": [-3.0, 0]}, {"type": "Point", "values": [0, 0]}, {"type": "Point", "values": [0.08333333333333333, 0.25]}, {"type": "Point", "values": [0.25, -0.25]}, {"type": "Point", "values": [0.41666666666666663, 0.25]}, {"type": "Point", "values": [0.5833333333333333, -0.25]}, {"type": "Point", "values": [0.75, 0.25]}, {"type": "Point", "values": [0.9166666666666666, -0.25]}, {"type": "Point", "values": [1.0, 0]}, {"type": "Point", "values": [4.0, 0]}], "zorder": null, "color": null, "fill": null, "lw": null, "ls": null, "arrow": null, "arrowwidth": 0.15, "arrowlength": 0.25, "clip": null, "capstyle": null, "joinstyle": null, "visible": true}}, {"type": "SegmentText", "values": {"pos": {"type": "Point", "values": [0.5, -0.5]}, "label": "Z3=30.0\u03a9", "align": ["center", "center"], "font": "sans-serif", "mathfont": null, "fontsize": 14.0, "color": "black", "rotation": 90, "rotation_mode": null, "rotation_global": true, "clip": null, "zorder": null, "visible": true}}], "params": {"unit": 7, "inches_per_unit": 0.5, "lblofst": 0.1, "fontsize": 14.0, "font": "sans-serif", "color": "black", "lw": 2.0, "ls": "-", "fill": null, "margin": 0.1, "leadcolor": null, "dotradius": 0.075, "Z": 30, "name": "Z3", "reverse": false, "d": "down", "drop": {"type": "Point", "values": [4.0, 0]}}, "anchors": {"value_label": [0.5, -0.6], "v_label": [0.5, 0.3], "s_label": [0.5, -1.2], "istart": {"type": "Point", "values": [0, 0]}, "iend": {"type": "Point", "values": [1.0, 0]}, "start": {"type": "Point", "values": [-3.0, 0]}, "end": {"type": "Point", "values": [4.0, 0]}, "center": {"type": "Point", "values": [0.5, 0.0]}}, "absanchors": {"start": {"type": "Point", "values": [14.0, 7.0]}, "end": {"type": "Point", "values": [13.999999999999998, 0.0]}, "center": {"type": "Point", "values": [14.0, 3.5]}, "value_label": {"type": "Point", "values": [13.399999999999999, 3.5]}, "v_label": {"type": "Point", "values": [14.299999999999999, 3.5]}, "s_label": {"type": "Point", "values": [12.799999999999999, 3.5]}, "istart": {"type": "Point", "values": [14.0, 4.0]}, "iend": {"type": "Point", "values": [14.0, 3.0]}, "xy": {"type": "Point", "values": [14.0, 4.0]}}, "transform": {"type": "Transform", "values": {"theta": 270, "globalshift": {"type": "Point", "values": [14.0, 7.0]}, "localshift": {"type": "Point", "values": [3.0, 0]}, "zoom": {"type": "Point", "values": [1, 1]}}}, "absdrop": [{"type": "Point", "values": [13.999999999999998, 0.0]}, 270]}}, {"type": "line", "name": "", "reverse": false, "values": {"_userparams": {"d": "left", "drop": {"type": "Point", "values": [3.5, 0]}}, "segments": [{"type": "Segment", "values": {"path": [{"type": "Point", "values": [-3.5, 0]}, {"type": "Point", "values": [0, 0]}, {"type": "Point", "values": [3.5, 0]}], "zorder": null, "color": null, "fill": null, "lw": null, "ls": null, "arrow": null, "arrowwidth": 0.15, "arrowlength": 0.25, "clip": null, "capstyle": null, "joinstyle": null, "visible": true}}], "params": {"unit": 7, "inches_per_unit": 0.5, "lblofst": 0.1, "fontsize": 14.0, "font": "sans-serif", "color": "black", "lw": 2.0, "ls": "-", "fill": null, "margin": 0.1, "leadcolor": null, "dotradius": 0.075, "arrowwidth": 0.15, "arrowlength": 0.25, "d": "left", "drop": {"type": "Point", "values": [3.5, 0]}}, "anchors": {"istart": {"type": "Point", "values": [0, 0]}, "iend": {"type": "Point", "values": [0, 0]}, "start": {"type": "Point", "values": [-3.5, 0]}, "end": {"type": "Point", "values": [3.5, 0]}, "center": {"type": "Point", "values": [0.0, 0.0]}}, "absanchors": {"start": {"type": "Point", "values": [13.999999999999998, 0.0]}, "end": {"type": "Point", "values": [6.999999999999998, 8.572527594031472e-16]}, "center": {"type": "Point", "values": [10.499999999999998, 4.286263797015736e-16]}, "istart": {"type": "Point", "values": [10.499999999999998, 4.286263797015736e-16]}, "iend": {"type": "Point", "values": [10.499999999999998, 4.286263797015736e-16]}, "xy": {"type": "Point", "values": [10.499999999999998, 4.286263797015736e-16]}}, "transform": {"type": "Transform", "values": {"theta": 180, "globalshift": {"type": "Point", "values": [13.999999999999998, 0.0]}, "localshift": {"type": "Point", "values": [3.5, 0]}, "zoom": {"type": "Point", "values": [1, 1]}}}, "absdrop": [{"type": "Point", "values": [6.999999999999998, 8.572527594031472e-16]}, 180]}}]}